[{"name":"Adana","districts":[{"name":"Aladağ","population":16121,"area":1340},{"name":"Ceyhan","population":160977,"area":1426},{"name":"Çukurova","population":376390,"area":250},{"name":"Feke","population":16919,"area":1218},{"name":"İmamoğlu","population":27938,"area":445},{"name":"Karaisalı","population":21948,"area":1165},{"name":"Karataş","population":23678,"area":862},{"name":"Kozan","population":131633,"area":1903},{"name":"Pozantı","population":19974,"area":899},{"name":"Saimbeyli","population":14764,"area":989},{"name":"Sarıçam","population":181610,"area":770},{"name":"Seyhan","population":796286,"area":444},{"name":"Tufanbeyli","population":17102,"area":851},{"name":"Yumurtalık","population":18026,"area":447},{"name":"Yüreğir","population":414574,"area":835}]},
{"name":"Adıyaman","districts":[{"name":"Besni","population":76674,"area":67},{"name":"Çelikhan","population":15470,"area":20},{"name":"Gerger","population":17552,"area":45},{"name":"Gölbaşı","population":49253,"area":30},{"name":"Kahta","population":123861,"area":102},{"name":"Merkez","population":308915,"area":135},{"name":"Samsat","population":7980,"area":16},{"name":"Sincik","population":16855,"area":24},{"name":"Tut","population":9905,"area":14}]},
{"name":"Afyonkarahisar","districts":[{"name":"Başmakçı","population":9788,"area":14},{"name":"Bayat","population":7673,"area":12},{"name":"Bolvadin","population":45384,"area":14},{"name":"Çay","population":31179,"area":20},{"name":"Çobanlar","population":14363,"area":3},{"name":"Dazkırı","population":11204,"area":16},{"name":"Dinar","population":47400,"area":60},{"name":"Emirdağ","population":37361,"area":69},{"name":"Evciler","population":7367,"area":7},{"name":"Hocalar","population":9496,"area":15},{"name":"İhsaniye","population":27929,"area":26},{"name":"İscehisar","population":24683,"area":11},{"name":"Kızılören","population":2329,"area":4},{"name":"Merkez","population":306908,"area":22},{"name":"Sandıklı","population":55331,"area":56},{"name":"Sinanpaşa","population":39734,"area":26},{"name":"Sultandağı","population":14566,"area":11},{"name":"Şuhut","population":36788,"area":36}]},
{"name":"Ağrı","districts":[{"name":"Diyadin","population":41512,"area":62},{"name":"Doğubayazıt","population":119807,"area":85},{"name":"Eleşkirt","population":32593,"area":55},{"name":"Hamur","population":18152,"area":46},{"name":"Merkez","population":151083,"area":106},{"name":"Patnos","population":122850,"area":92},{"name":"Taşlıçay","population":20029,"area":37},{"name":"Tutak","population":30173,"area":80}]},
{"name":"Aksaray","districts":[{"name":"Ağaçören","population":7972,"area":27},{"name":"Eskil","population":26452,"area":11},{"name":"Gülağaç","population":19615,"area":9},{"name":"Güzelyurt","population":11223,"area":8},{"name":"Merkez","population":301661,"area":83},{"name":"Ortaköy","population":32639,"area":30},{"name":"Sarıyahşi","population":5658,"area":6},{"name":"Sultanhanı","population":11147,"area":1}]},
{"name":"Amasya","districts":[{"name":"Göynücek","population":10207,"area":38},{"name":"Gümüşhacıköy","population":23402,"area":44},{"name":"Hamamözü","population":3802,"area":17},{"name":"Merkez","population":150828,"area":100},{"name":"Merzifon","population":72277,"area":70},{"name":"Suluova","population":46649,"area":40},{"name":"Taşova","population":30635,"area":63}]},
{"name":"Ankara","districts":[{"name":"Akyurt","population":36123,"area":369},{"name":"Altındağ","population":389510,"area":123},{"name":"Ayaş","population":13900,"area":1041},{"name":"Bala","population":30280,"area":1851},{"name":"Beypazarı","population":48371,"area":1697},{"name":"Çamlıdere","population":9825,"area":782},{"name":"Çankaya","population":944609,"area":483},{"name":"Çubuk","population":90764,"area":1198},{"name":"Elmadağ","population":45557,"area":647},{"name":"Etimesgut","population":587052,"area":273},{"name":"Evren","population":3097,"area":222},{"name":"Gölbaşı","population":138944,"area":1364},{"name":"Güdül","population":8892,"area":540},{"name":"Haymana","population":30930,"area":2164},{"name":"Kahramankazan","population":54806,"area":547},{"name":"Kalecik","population":13234,"area":1110},{"name":"Keçiören","population":939161,"area":159},{"name":"Kızılcahamam","population":28350,"area":1623},{"name":"Mamak","population":665978,"area":321},{"name":"Nallıhan","population":27579,"area":2079},{"name":"Polatlı","population":125075,"area":3618},{"name":"Pursaklar","population":150488,"area":169},{"name":"Sincan","population":535637,"area":880},{"name":"Şereflikoçhisar","population":33821,"area":2155},{"name":"Yenimahalle","population":687093,"area":219}]},
{"name":"Antalya","districts":[{"name":"Akseki","population":11484,"area":1544},{"name":"Aksu","population":73220,"area":406},{"name":"Alanya","population":327503,"area":1577},{"name":"Demre","population":26362,"area":329},{"name":"Döşemealtı","population":65794,"area":687},{"name":"Elmalı","population":38972,"area":1433},{"name":"Finike","population":48534,"area":768},{"name":"Gazipaşa","population":50555,"area":1111},{"name":"Gündoğmuş","population":7737,"area":1175},{"name":"İbradı","population":3032,"area":778},{"name":"Kaş","population":59716,"area":1750},{"name":"Kemer","population":46143,"area":412},{"name":"Kepez","population":556033,"area":292},{"name":"Konyaaltı","population":190043,"area":546},{"name":"Korkuteli","population":55352,"area":2433},{"name":"Kumluca","population":70423,"area":1225},{"name":"Manavgat","population":241011,"area":2351},{"name":"Muratpaşa","population":510368,"area":96},{"name":"Serik","population":129418,"area":1263}]},
{"name":"Ardahan","districts":[{"name":"Çıldır","population":9343,"area":34},{"name":"Damal","population":5334,"area":7},{"name":"Göle","population":24863,"area":49},{"name":"Hanak","population":8776,"area":26},{"name":"Merkez","population":42374,"area":62},{"name":"Posof","population":6629,"area":48}]},
{"name":"Artvin","districts":[{"name":"Ardanuç","population":11449,"area":49},{"name":"Arhavi","population":20926,"area":30},{"name":"Borçka","population":22831,"area":38},{"name":"Hopa","population":26958,"area":16},{"name":"Kemalpaşa","population":9224,"area":12},{"name":"Merkez","population":35186,"area":36},{"name":"Murgul","population":7031,"area":11},{"name":"Şavşat","population":17116,"area":65},{"name":"Yusufeli","population":20154,"area":63}]},
{"name":"Aydın","districts":[{"name":"Bozdoğan","population":33627,"area":859},{"name":"Buharkent","population":12793,"area":124},{"name":"Çine","population":49339,"area":820},{"name":"Didim","population":86688,"area":424},{"name":"Efeler","population":293816,"area":624},{"name":"Germencik","population":43968,"area":394},{"name":"İncirliova","population":52556,"area":188},{"name":"Karacasu","population":18389,"area":727},{"name":"Karpuzlu","population":10952,"area":286},{"name":"Koçarlı","population":23397,"area":455},{"name":"Köşk","population":27846,"area":187},{"name":"Kuşadası","population":116966,"area":265},{"name":"Kuyucak","population":26671,"area":544},{"name":"Nazilli","population":159544,"area":691},{"name":"Söke","population":121481,"area":1064},{"name":"Sultanhisar","population":20458,"area":220},{"name":"Yenipazar","population":12481,"area":245}]},
{"name":"Balıkesir","districts":[{"name":"Altıeylül","population":181286,"area":956},{"name":"Ayvalık","population":70720,"area":305},{"name":"Balya","population":12932,"area":797},{"name":"Bandırma","population":156787,"area":755},{"name":"Bigadiç","population":49926,"area":1108},{"name":"Burhaniye","population":60490,"area":420},{"name":"Dursunbey","population":35122,"area":1719},{"name":"Edremit","population":155837,"area":682},{"name":"Erdek","population":32120,"area":307},{"name":"Gömeç","population":14175,"area":171},{"name":"Gönen","population":74183,"area":1162},{"name":"Havran","population":27857,"area":565},{"name":"İvrindi","population":32492,"area":818},{"name":"Karesi","population":183084,"area":695},{"name":"Kepsut","population":23142,"area":889},{"name":"Manyas","population":18936,"area":634},{"name":"Marmara","population":9730,"area":134},{"name":"Savaştepe","population":17844,"area":427},{"name":"Sındırgı","population":33253,"area":1387},{"name":"Susurluk","population":38704,"area":652}]},
{"name":"Bartın","districts":[{"name":"Amasra","population":14151,"area":30},{"name":"Kurucaşile","population":6621,"area":28},{"name":"Merkez","population":155765,"area":137},{"name":"Ulus","population":21712,"area":68}]},
{"name":"Batman","districts":[{"name":"Beşiri","population":29667,"area":53},{"name":"Gercüş","population":19892,"area":58},{"name":"Hasankeyf","population":6859,"area":21},{"name":"Kozluk","population":60375,"area":69},{"name":"Merkez","population":460955,"area":32},{"name":"Sason","population":30911,"area":50}]},
{"name":"Bayburt","districts":[{"name":"Aydıntepe","population":6825,"area":23},{"name":"Demirözü","population":9247,"area":26},{"name":"Merkez","population":68771,"area":121}]},
{"name":"Bilecik","districts":[{"name":"Bozüyük","population":75566,"area":44},{"name":"Gölpazarı","population":10464,"area":48},{"name":"İnhisar","population":2414,"area":9},{"name":"Merkez","population":78533,"area":46},{"name":"Osmaneli","population":21105,"area":27},{"name":"Pazaryeri","population":10301,"area":24},{"name":"Söğüt","population":18167,"area":23},{"name":"Yenipazar","population":2877,"area":23}]},
{"name":"Bingöl","districts":[{"name":"Adaklı","population":8550,"area":32},{"name":"Genç","population":34181,"area":68},{"name":"Karlıova","population":29174,"area":47},{"name":"Kiğı","population":4578,"area":25},{"name":"Merkez","population":164835,"area":88},{"name":"Solhan","population":33655,"area":27},{"name":"Yayladere","population":2021,"area":20},{"name":"Yedisu","population":2818,"area":13}]},
{"name":"Bitlis","districts":[{"name":"Adilcevaz","population":30499,"area":28},{"name":"Ahlat","population":40699,"area":26},{"name":"Güroymak","population":47829,"area":26},{"name":"Hizan","population":33331,"area":75},{"name":"Merkez","population":70699,"area":76},{"name":"Mutki","population":31869,"area":60},{"name":"Tatvan","population":93189,"area":57}]},
{"name":"Bolu","districts":[{"name":"Dörtdivan","population":6750,"area":24},{"name":"Gerede","population":33926,"area":92},{"name":"Göynük","population":15050,"area":66},{"name":"Kıbrıscık","population":3179,"area":22},{"name":"Mengen","population":13953,"area":56},{"name":"Merkez","population":212358,"area":112},{"name":"Mudurnu","population":18880,"area":70},{"name":"Seben","population":5083,"area":29},{"name":"Yeniçağa","population":6947,"area":16}]},
{"name":"Burdur","districts":[{"name":"Ağlasun","population":8078,"area":9},{"name":"Altınyayla","population":5519,"area":5},{"name":"Bucak","population":65335,"area":35},{"name":"Çavdır","population":12796,"area":10},{"name":"Çeltikçi","population":5134,"area":6},{"name":"Gölhisar","population":22399,"area":12},{"name":"Karamanlı","population":8016,"area":8},{"name":"Kemer","population":3217,"area":7},{"name":"Merkez","population":115159,"area":51},{"name":"Tefenni","population":9918,"area":14},{"name":"Yeşilova","population":15225,"area":36}]},
{"name":"Bursa","districts":[{"name":"Büyükorhan","population":9666,"area":505},{"name":"Gemlik","population":113493,"area":401},{"name":"Gürsu","population":93788,"area":106},{"name":"Harmancık","population":6384,"area":400},{"name":"İnegöl","population":273933,"area":1118},{"name":"İznik","population":43531,"area":753},{"name":"Karacabey","population":83923,"area":1158},{"name":"Keles","population":11997,"area":617},{"name":"Kestel","population":68204,"area":396},{"name":"Mudanya","population":97631,"area":369},{"name":"Mustafakemalpaşa","population":101119,"area":1641},{"name":"Nilüfer","population":465956,"area":552},{"name":"Orhaneli","population":19387,"area":838},{"name":"Orhangazi","population":79145,"area":506},{"name":"Osmangazi","population":876048,"area":621},{"name":"Yenişehir","population":53921,"area":720},{"name":"Yıldırım","population":657994,"area":110}]},
{"name":"Çanakkale","districts":[{"name":"Ayvacık","population":33356,"area":64},{"name":"Bayramiç","population":29400,"area":75},{"name":"Biga","population":90418,"area":108},{"name":"Bozcaada","population":2988,"area":0},{"name":"Çan","population":48461,"area":65},{"name":"Eceabat","population":8784,"area":12},{"name":"Ezine","population":30660,"area":49},{"name":"Gelibolu","population":44346,"area":26},{"name":"Gökçeada","population":9440,"area":9},{"name":"Lapseki","population":27838,"area":40},{"name":"Merkez","population":184631,"area":52},{"name":"Yenice","population":31835,"area":76}]},
{"name":"Çankırı","districts":[{"name":"Atkaracalar","population":5534,"area":8},{"name":"Bayramören","population":2924,"area":27},{"name":"Çerkeş","population":16792,"area":49},{"name":"Eldivan","population":6460,"area":16},{"name":"Ilgaz","population":14098,"area":75},{"name":"Kızılırmak","population":7304,"area":26},{"name":"Korgun","population":4626,"area":12},{"name":"Kurşunlu","population":8466,"area":27},{"name":"Merkez","population":97882,"area":50},{"name":"Orta","population":11978,"area":25},{"name":"Şabanözü","population":11869,"area":18},{"name":"Yapraklı","population":7856,"area":38}]},
{"name":"Çorum","districts":[{"name":"Alaca","population":31121,"area":101},{"name":"Bayat","population":16093,"area":40},{"name":"Boğazkale","population":3766,"area":14},{"name":"Dodurga","population":5931,"area":12},{"name":"İskilip","population":31892,"area":64},{"name":"Kargı","population":15455,"area":58},{"name":"Laçin","population":4599,"area":14},{"name":"Mecitözü","population":14934,"area":54},{"name":"Merkez","population":297224,"area":198},{"name":"Oğuzlar","population":5252,"area":6},{"name":"Ortaköy","population":7069,"area":14},{"name":"Osmancık","population":42954,"area":55},{"name":"Sungurlu","population":48158,"area":109},{"name":"Uğurludağ","population":6416,"area":20}]},
{"name":"Denizli","districts":[{"name":"Acıpayam","population":55351,"area":1772},{"name":"Babadağ","population":6445,"area":124},{"name":"Baklan","population":5524,"area":283},{"name":"Bekilli","population":6826,"area":304},{"name":"Beyağaç","population":6397,"area":333},{"name":"Bozkurt","population":12671,"area":462},{"name":"Buldan","population":27179,"area":523},{"name":"Çal","population":18869,"area":860},{"name":"Çameli","population":18039,"area":758},{"name":"Çardak","population":8736,"area":423},{"name":"Çivril","population":60333,"area":1570},{"name":"Güney","population":9802,"area":362},{"name":"Honaz","population":34343,"area":449},{"name":"Kale","population":20310,"area":684},{"name":"Merkezefendi","population":311177,"area":336},{"name":"Pamukkale","population":346625,"area":823},{"name":"Sarayköy","population":30810,"area":379},{"name":"Serinhisar","population":14451,"area":256},{"name":"Tavas","population":43320,"area":1432}]},
{"name":"Diyarbakır","districts":[{"name":"Bağlar","population":396102,"area":429},{"name":"Bismil","population":118250,"area":1679},{"name":"Çermik","population":50819,"area":948},{"name":"Çınar","population":75640,"area":1934},{"name":"Çüngüş","population":11539,"area":512},{"name":"Dicle","population":37673,"area":738},{"name":"Eğil","population":22704,"area":449},{"name":"Ergani","population":132463,"area":1510},{"name":"Hani","population":32675,"area":436},{"name":"Hazro","population":16618,"area":426},{"name":"Kayapınar","population":381414,"area":480},{"name":"Kocaköy","population":16106,"area":248},{"name":"Kulp","population":35357,"area":1560},{"name":"Lice","population":25222,"area":982},{"name":"Silvan","population":86736,"area":1252},{"name":"Sur","population":106108,"area":1227},{"name":"Yenişehir","population":210927,"area":358}]},
{"name":"Düzce","districts":[{"name":"Akçakoca","population":38639,"area":43},{"name":"Cumayeri","population":14649,"area":21},{"name":"Çilimli","population":19976,"area":20},{"name":"Gölyaka","population":20179,"area":21},{"name":"Gümüşova","population":15842,"area":18},{"name":"Kaynaşlı","population":20454,"area":20},{"name":"Merkez","population":247419,"area":96},{"name":"Yığılca","population":15008,"area":39}]},
{"name":"Edirne","districts":[{"name":"Enez","population":10583,"area":19},{"name":"Havsa","population":18648,"area":22},{"name":"İpsala","population":27246,"area":19},{"name":"Keşan","population":83373,"area":45},{"name":"Lalapaşa","population":6590,"area":27},{"name":"Meriç","population":13681,"area":21},{"name":"Merkez","population":185408,"area":37},{"name":"Süloğlu","population":7287,"area":10},{"name":"Uzunköprü","population":61087,"area":53},{"name":"EDİRNE  ","population":413903,"area":253}]},
{"name":"Elazığ","districts":[{"name":"Ağın","population":2626,"area":16},{"name":"Alacakaya","population":6151,"area":10},{"name":"Arıcak","population":14620,"area":10},{"name":"Baskil","population":13764,"area":60},{"name":"Karakoçan","population":28142,"area":88},{"name":"Keban","population":7068,"area":30},{"name":"Kovancılar","population":39079,"area":76},{"name":"Maden","population":11275,"area":38},{"name":"Merkez","population":439687,"area":135},{"name":"Palu","population":19776,"area":37},{"name":"Sivrice","population":8910,"area":50}]},
{"name":"Erzincan","districts":[{"name":"Çayırlı","population":8582,"area":47},{"name":"İliç","population":8877,"area":58},{"name":"Kemah","population":6697,"area":73},{"name":"Kemaliye","population":5106,"area":61},{"name":"Merkez","population":161191,"area":59},{"name":"Otlukbeli","population":2333,"area":10},{"name":"Refahiye","population":11593,"area":121},{"name":"Tercan","population":16875,"area":70},{"name":"Üzümlü","population":13493,"area":23}]},
{"name":"Erzurum","districts":[{"name":"Aşkale","population":23152,"area":1507},{"name":"Aziziye","population":63502,"area":1529},{"name":"Çat","population":16708,"area":1448},{"name":"Hınıs","population":26212,"area":1367},{"name":"Horasan","population":38837,"area":1740},{"name":"İspir","population":14959,"area":2129},{"name":"Karaçoban","population":23322,"area":571},{"name":"Karayazı","population":27762,"area":1953},{"name":"Köprüköy","population":15784,"area":777},{"name":"Narman","population":13326,"area":799},{"name":"Oltu","population":30511,"area":1441},{"name":"Olur","population":6469,"area":893},{"name":"Palandöken","population":172337,"area":667},{"name":"Pasinler","population":28691,"area":1134},{"name":"Pazaryolu","population":3975,"area":654},{"name":"Şenkaya","population":17511,"area":1381},{"name":"Tekman","population":25723,"area":2102},{"name":"Tortum","population":18135,"area":1463},{"name":"Uzundere","population":8153,"area":505},{"name":"Yakutiye","population":186993,"area":945}]},
{"name":"Eskişehir","districts":[{"name":"Alpu","population":10974,"area":1028},{"name":"Beylikova","population":6400,"area":715},{"name":"Çifteler","population":14878,"area":858},{"name":"Günyüzü","population":5671,"area":828},{"name":"Han","population":2117,"area":378},{"name":"İnönü","population":6514,"area":345},{"name":"Mahmudiye","population":7808,"area":659},{"name":"Mihalgazi","population":3138,"area":109},{"name":"Mihalıççık","population":8171,"area":1809},{"name":"Odunpazarı","population":413461,"area":1120},{"name":"Sarıcakaya","population":4854,"area":382},{"name":"Seyitgazi","population":13009,"area":1578},{"name":"Sivrihisar","population":20330,"area":2748},{"name":"Tepebaşı","population":370150,"area":1403}]},
{"name":"Gaziantep","districts":[{"name":"Araban","population":32761,"area":392},{"name":"İslahiye","population":67023,"area":592},{"name":"Karkamış","population":9806,"area":865},{"name":"Nizip","population":143994,"area":298},{"name":"Nurdağı","population":40221,"area":944},{"name":"Oğuzeli","population":31879,"area":697},{"name":"Şahinbey","population":926544,"area":689},{"name":"Şehitkamil","population":794931,"area":960},{"name":"Yavuzeli","population":22205,"area":1290}]},
{"name":"Giresun","districts":[{"name":"Alucra","population":10253,"area":38},{"name":"Bulancak","population":67582,"area":59},{"name":"Çamoluk","population":8289,"area":27},{"name":"Çanakçı","population":6232,"area":15},{"name":"Dereli","population":19731,"area":34},{"name":"Doğankent","population":6613,"area":9},{"name":"Espiye","population":35649,"area":31},{"name":"Eynesil","population":13293,"area":11},{"name":"Görele","population":31862,"area":61},{"name":"Güce","population":7992,"area":15},{"name":"Keşap","population":19630,"area":44},{"name":"Merkez","population":138858,"area":53},{"name":"Piraziz","population":14310,"area":22},{"name":"Şebinkarahisar","population":20459,"area":62},{"name":"Tirebolu","population":31854,"area":49},{"name":"Yağlıdere","population":15793,"area":21}]},
{"name":"Gümüşhane","districts":[{"name":"Kelkit","population":52608,"area":77},{"name":"Köse","population":8349,"area":14},{"name":"Kürtün","population":13376,"area":34},{"name":"Merkez","population":56398,"area":92},{"name":"Şiran","population":21286,"area":64},{"name":"Torul","population":12504,"area":37}]},
{"name":"Hakkâri","districts":[{"name":"Çukurca","population":16141,"area":8},{"name":"Derecik","population":23377,"area":4},{"name":"Merkez","population":78672,"area":36},{"name":"Şemdinli","population":43886,"area":18},{"name":"Yüksekova","population":118915,"area":58}]},
{"name":"Hatay","districts":[{"name":"Altınözü","population":60745,"area":468},{"name":"Antakya","population":383354,"area":703},{"name":"Arsuz","population":92749,"area":462},{"name":"Belen","population":33313,"area":184},{"name":"Defne","population":154820,"area":155},{"name":"Dörtyol","population":125138,"area":342},{"name":"Erzin","population":41463,"area":258},{"name":"Hassa","population":56519,"area":520},{"name":"İskenderun","population":248380,"area":247},{"name":"Kırıkhan","population":116876,"area":715},{"name":"Kumlu","population":13686,"area":193},{"name":"Payas","population":42477,"area":157},{"name":"Reyhanlı","population":100151,"area":367},{"name":"Samandağ","population":122223,"area":384},{"name":"Yayladağı","population":37000,"area":445}]},
{"name":"Iğdır","districts":[{"name":"Aralık","population":21313,"area":21},{"name":"Karakoyunlu","population":13925,"area":18},{"name":"Merkez","population":140267,"area":41},{"name":"Tuzluca","population":23937,"area":81}]},
{"name":"Isparta","districts":[{"name":"Aksu","population":4557,"area":13},{"name":"Atabey","population":5761,"area":5},{"name":"Eğirdir","population":31632,"area":29},{"name":"Gelendost","population":15298,"area":13},{"name":"Gönen","population":7185,"area":5},{"name":"Keçiborlu","population":14152,"area":14},{"name":"Merkez","population":264426,"area":20},{"name":"Senirkent","population":11395,"area":7},{"name":"Sütçüler","population":10295,"area":30},{"name":"Şarkikaraağaç","population":25151,"area":26},{"name":"Uluborlu","population":6287,"area":4},{"name":"Yalvaç","population":46688,"area":37},{"name":"Yenişarbademli","population":2087,"area":1}]},
{"name":"İstanbul","districts":[{"name":"Adalar","population":15238,"area":11},{"name":"Arnavutköy","population":282488,"area":453},{"name":"Ataşehir","population":425094,"area":25},{"name":"Avcılar","population":448882,"area":50},{"name":"Bağcılar","population":745125,"area":23},{"name":"Bahçelievler","population":611059,"area":17},{"name":"Bakırköy","population":229239,"area":29},{"name":"Başakşehir","population":460259,"area":107},{"name":"Bayrampaşa","population":274735,"area":9},{"name":"Beşiktaş","population":182649,"area":18},{"name":"Beykoz","population":248260,"area":310},{"name":"Beylikdüzü","population":352412,"area":39},{"name":"Beyoğlu","population":233323,"area":9},{"name":"Büyükçekmece","population":254103,"area":173},{"name":"Çatalca","population":73718,"area":1142},{"name":"Çekmeköy","population":264508,"area":152},{"name":"Esenler","population":450344,"area":19},{"name":"Esenyurt","population":954579,"area":43},{"name":"Eyüpsultan","population":400513,"area":228},{"name":"Fatih","population":443090,"area":15},{"name":"Gaziosmanpaşa","population":491962,"area":12},{"name":"Güngören","population":289441,"area":7},{"name":"Kadıköy","population":482713,"area":25},{"name":"Kağıthane","population":448025,"area":15},{"name":"Kartal","population":470676,"area":38},{"name":"Küçükçekmece","population":792821,"area":44},{"name":"Maltepe","population":513316,"area":53},{"name":"Pendik","population":711894,"area":190},{"name":"Sancaktepe","population":436733,"area":63},{"name":"Sarıyer","population":347214,"area":177},{"name":"Silivri","population":193680,"area":858},{"name":"Sultanbeyli","population":336021,"area":29},{"name":"Sultangazi","population":534565,"area":37},{"name":"Şile","population":37692,"area":800},{"name":"Şişli","population":279817,"area":10},{"name":"Tuzla","population":267400,"area":138},{"name":"Ümraniye","population":710280,"area":46},{"name":"Üsküdar","population":531825,"area":35},{"name":"Zeytinburnu","population":293574,"area":12}]},
{"name":"İzmir","districts":[{"name":"Aliağa","population":96974,"area":379},{"name":"Balçova","population":79681,"area":16},{"name":"Bayındır","population":40414,"area":548},{"name":"Bayraklı","population":312264,"area":30},{"name":"Bergama","population":103867,"area":1544},{"name":"Beydağ","population":12340,"area":172},{"name":"Bornova","population":450992,"area":220},{"name":"Buca","population":510695,"area":178},{"name":"Çeşme","population":44363,"area":285},{"name":"Çiğli","population":200211,"area":139},{"name":"Dikili","population":43806,"area":534},{"name":"Foça","population":32264,"area":251},{"name":"Gaziemir","population":137808,"area":70},{"name":"Güzelbahçe","population":33725,"area":77},{"name":"Karabağlar","population":480925,"area":89},{"name":"Karaburun","population":10759,"area":421},{"name":"Karşıyaka","population":349290,"area":51},{"name":"Kemalpaşa","population":107556,"area":681},{"name":"Kınık","population":28802,"area":479},{"name":"Kiraz","population":43925,"area":573},{"name":"Konak","population":351572,"area":24},{"name":"Menderes","population":97123,"area":777},{"name":"Menemen","population":179881,"area":573},{"name":"Narlıdere","population":65737,"area":50},{"name":"Ödemiş","population":132876,"area":1019},{"name":"Seferihisar","population":44526,"area":375},{"name":"Selçuk","population":36824,"area":317},{"name":"Tire","population":84804,"area":716},{"name":"Torbalı","population":185908,"area":577},{"name":"Urla","population":67339,"area":727}]},
{"name":"Kahramanmaraş","districts":[{"name":"Afşin","population":80447,"area":1502},{"name":"Andırın","population":32503,"area":1202},{"name":"Çağlayancerit","population":23133,"area":470},{"name":"Dulkadiroğlu","population":222673,"area":1176},{"name":"Ekinözü","population":11221,"area":656},{"name":"Elbistan","population":141534,"area":2201},{"name":"Göksun","population":52255,"area":1942},{"name":"Nurhak","population":12279,"area":1028},{"name":"Onikişubat","population":431848,"area":2429},{"name":"Pazarcık","population":69097,"area":1253},{"name":"Türkoğlu","population":77112,"area":660}]},
{"name":"Karabük","districts":[{"name":"Eflani","population":8823,"area":54},{"name":"Eskipazar","population":12996,"area":50},{"name":"Merkez","population":133615,"area":37},{"name":"Ovacık","population":4274,"area":42},{"name":"Safranbolu","population":68440,"area":60},{"name":"Yenice","population":20310,"area":34}]},
{"name":"Karaman","districts":[{"name":"Ayrancı","population":7965,"area":22},{"name":"Başyayla","population":3650,"area":4},{"name":"Ermenek","population":28565,"area":26},{"name":"Kazımkarabekir","population":4328,"area":6},{"name":"Merkez","population":197276,"area":93},{"name":"Sarıveliler","population":11495,"area":7}]},
{"name":"Kars","districts":[{"name":"Akyaka","population":10584,"area":27},{"name":"Arpaçay","population":16645,"area":48},{"name":"Digor","population":21730,"area":37},{"name":"Kağızman","population":45505,"area":62},{"name":"Merkez","population":116712,"area":72},{"name":"Sarıkamış","population":41280,"area":55},{"name":"Selim","population":22910,"area":53},{"name":"Susuz","population":10044,"area":27}]},
{"name":"Kastamonu","districts":[{"name":"Abana","population":4113,"area":10},{"name":"Ağlı","population":3094,"area":13},{"name":"Araç","population":18670,"area":119},{"name":"Azdavay","population":7324,"area":49},{"name":"Bozkurt","population":9468,"area":32},{"name":"Cide","population":22196,"area":75},{"name":"Çatalzeytin","population":7055,"area":41},{"name":"Daday","population":8319,"area":60},{"name":"Devrekani","population":12658,"area":54},{"name":"Doğanyurt","population":5651,"area":25},{"name":"Hanönü","population":4060,"area":20},{"name":"İhsangazi","population":5381,"area":23},{"name":"İnebolu","population":20980,"area":77},{"name":"Küre","population":5774,"area":34},{"name":"Merkez","population":152553,"area":177},{"name":"Pınarbaşı","population":5841,"area":27},{"name":"Seydiler","population":4014,"area":15},{"name":"Şenpazar","population":4523,"area":23},{"name":"Taşköprü","population":37815,"area":126},{"name":"Tosya","population":39916,"area":54}]},
{"name":"Kayseri","districts":[{"name":"Akkışla","population":6247,"area":371},{"name":"Bünyan","population":30603,"area":1210},{"name":"Develi","population":65745,"area":1892},{"name":"Felahiye","population":5861,"area":444},{"name":"Hacılar","population":12414,"area":187},{"name":"İncesu","population":27969,"area":874},{"name":"Kocasinan","population":396912,"area":1471},{"name":"Melikgazi","population":571166,"area":668},{"name":"Özvatan","population":4164,"area":270},{"name":"Pınarbaşı","population":24080,"area":3418},{"name":"Sarıoğlan","population":14552,"area":642},{"name":"Sarız","population":9583,"area":1173},{"name":"Talas","population":163773,"area":444},{"name":"Tomarza","population":22166,"area":1405},{"name":"Yahyalı","population":36076,"area":1587},{"name":"Yeşilhisar","population":16098,"area":913}]},
{"name":"Kırıkkale","districts":[{"name":"Bahşılı","population":7399,"area":5},{"name":"Balışeyh","population":6478,"area":28},{"name":"Çelebi","population":2633,"area":13},{"name":"Delice","population":9075,"area":40},{"name":"Karakeçili","population":3369,"area":2},{"name":"Keskin","population":17620,"area":55},{"name":"Merkez","population":198477,"area":9},{"name":"Sulakyurt","population":6953,"area":26},{"name":"Yahşihan","population":31013,"area":7}]},
{"name":"Kırklareli","districts":[{"name":"Babaeski","population":47944,"area":31},{"name":"Demirköy","population":8856,"area":15},{"name":"Kofçaz","population":2308,"area":16},{"name":"Lüleburgaz","population":149184,"area":31},{"name":"Merkez","population":103042,"area":40},{"name":"Pehlivanköy","population":3505,"area":8},{"name":"Pınarhisar","population":18456,"area":14},{"name":"Vize","population":28541,"area":24}]},
{"name":"Kırşehir","districts":[{"name":"Akçakent","population":3889,"area":20},{"name":"Akpınar","population":7465,"area":26},{"name":"Boztepe","population":5464,"area":14},{"name":"Çiçekdağı","population":14186,"area":45},{"name":"Kaman","population":35763,"area":50},{"name":"Merkez","population":157635,"area":53},{"name":"Mucur","population":18536,"area":44}]},
{"name":"Kilis","districts":[{"name":"Elbeyli","population":5986,"area":23},{"name":"Merkez","population":118033,"area":52},{"name":"Musabeyli","population":13334,"area":46},{"name":"Polateli","population":5137,"area":16}]},
{"name":"Kocaeli","districts":[{"name":"Başiskele","population":102241,"area":209},{"name":"Çayırova","population":134146,"area":23},{"name":"Darıca","population":207345,"area":23},{"name":"Derince","population":142849,"area":198},{"name":"Dilovası","population":50551,"area":125},{"name":"Gebze","population":382166,"area":418},{"name":"Gölcük","population":165663,"area":217},{"name":"İzmit","population":367990,"area":480},{"name":"Kandıra","population":51897,"area":840},{"name":"Karamürsel","population":57557,"area":262},{"name":"Kartepe","population":121326,"area":301},{"name":"Körfez","population":169304,"area":301}]},
{"name":"Konya","districts":[{"name":"Ahırlı","population":4753,"area":325},{"name":"Akören","population":5838,"area":640},{"name":"Akşehir","population":93885,"area":895},{"name":"Altınekin","population":14351,"area":1312},{"name":"Beyşehir","population":74469,"area":2054},{"name":"Bozkır","population":25894,"area":1105},{"name":"Cihanbeyli","population":51748,"area":3702},{"name":"Çeltik","population":9713,"area":640},{"name":"Çumra","population":67282,"area":2089},{"name":"Derbent","population":4267,"area":359},{"name":"Derebucak","population":6031,"area":451},{"name":"Doğanhisar","population":15810,"area":482},{"name":"Emirgazi","population":8535,"area":798},{"name":"Ereğli","population":146998,"area":2214},{"name":"Güneysınır","population":9288,"area":482},{"name":"Hadim","population":12015,"area":1165},{"name":"Halkapınar","population":4066,"area":605},{"name":"Hüyük","population":15652,"area":443},{"name":"Ilgın","population":54228,"area":1636},{"name":"Kadınhanı","population":32144,"area":1568},{"name":"Karapınar","population":49978,"area":2623},{"name":"Karatay","population":338976,"area":2832},{"name":"Kulu","population":50825,"area":2234},{"name":"Meram","population":344546,"area":1822},{"name":"Sarayönü","population":27026,"area":1620},{"name":"Selçuklu","population":662808,"area":1931},{"name":"Seydişehir","population":64822,"area":1458},{"name":"Taşkent","population":6296,"area":457},{"name":"Tuzlukçu","population":6529,"area":704},{"name":"Yalıhüyük","population":1629,"area":94},{"name":"Yunak","population":21972,"area":2101}]},
{"name":"Kütahya","districts":[{"name":"Altıntaş","population":16108,"area":35},{"name":"Aslanapa","population":8945,"area":31},{"name":"Çavdarhisar","population":6303,"area":23},{"name":"Domaniç","population":14652,"area":30},{"name":"Dumlupınar","population":2944,"area":10},{"name":"Emet","population":19864,"area":37},{"name":"Gediz","population":50274,"area":57},{"name":"Hisarcık","population":12069,"area":25},{"name":"Merkez","population":272367,"area":109},{"name":"Pazarlar","population":5086,"area":7},{"name":"Simav","population":63155,"area":83},{"name":"Şaphane","population":6030,"area":12},{"name":"Tavşanlı","population":101460,"area":87}]},
{"name":"Malatya","districts":[{"name":"Akçadağ","population":29064,"area":1118},{"name":"Arapgir","population":10275,"area":987},{"name":"Arguvan","population":7626,"area":1096},{"name":"Battalgazi","population":304787,"area":947},{"name":"Darende","population":26166,"area":1482},{"name":"Doğanşehir","population":38690,"area":1364},{"name":"Doğanyol","population":4051,"area":177},{"name":"Hekimhan","population":18345,"area":1514},{"name":"Kale","population":6085,"area":237},{"name":"Kuluncak","population":7783,"area":645},{"name":"Pütürge","population":13889,"area":1086},{"name":"Yazıhan","population":13786,"area":653},{"name":"Yeşilyurt","population":319618,"area":953}]},
{"name":"Manisa","districts":[{"name":"Ahmetli","population":16525,"area":227},{"name":"Akhisar","population":173026,"area":1645},{"name":"Alaşehir","population":104622,"area":971},{"name":"Demirci","population":40048,"area":1321},{"name":"Gölmarmara","population":15212,"area":310},{"name":"Gördes","population":27703,"area":902},{"name":"Kırkağaç","population":38459,"area":541},{"name":"Köprübaşı","population":13185,"area":447},{"name":"Kula","population":44001,"area":981},{"name":"Salihli","population":162787,"area":1359},{"name":"Sarıgöl","population":35890,"area":432},{"name":"Saruhanlı","population":55340,"area":771},{"name":"Selendi","population":19871,"area":726},{"name":"Soma","population":109946,"area":820},{"name":"Şehzadeler","population":171138,"area":515},{"name":"Turgutlu","population":166418,"area":549},{"name":"Yunusemre","population":246440,"area":823}]},
{"name":"Mardin","districts":[{"name":"Artuklu","population":178154,"area":885},{"name":"Dargeçit","population":27711,"area":519},{"name":"Derik","population":61706,"area":1381},{"name":"Kızıltepe","population":256664,"area":1236},{"name":"Mazıdağı","population":36304,"area":850},{"name":"Midyat","population":114763,"area":1241},{"name":"Nusaybin","population":108172,"area":1079},{"name":"Ömerli","population":14026,"area":458},{"name":"Savur","population":26583,"area":962},{"name":"Yeşilli","population":14695,"area":168}]},
{"name":"Mersin","districts":[{"name":"Akdeniz","population":262265,"area":265},{"name":"Anamur","population":66068,"area":1430},{"name":"Aydıncık","population":11023,"area":352},{"name":"Bozyazı","population":26595,"area":642},{"name":"Çamlıyayla","population":8326,"area":602},{"name":"Erdemli","population":141476,"area":2279},{"name":"Gülnar","population":25420,"area":1416},{"name":"Mezitli","population":204240,"area":371},{"name":"Mut","population":62639,"area":2718},{"name":"Silifke","population":120873,"area":2692},{"name":"Tarsus","population":342373,"area":2029},{"name":"Toroslar","population":303010,"area":1075},{"name":"Yenişehir","population":266117,"area":139}]},
{"name":"Muğla","districts":[{"name":"Bodrum","population":175435,"area":650},{"name":"Dalaman","population":42024,"area":608},{"name":"Datça","population":22403,"area":436},{"name":"Fethiye","population":162686,"area":875},{"name":"Kavaklıdere","population":10792,"area":302},{"name":"Köyceğiz","population":36926,"area":1329},{"name":"Marmaris","population":94749,"area":906},{"name":"Menteşe","population":115059,"area":1659},{"name":"Milas","population":141107,"area":2067},{"name":"Ortaca","population":50027,"area":285},{"name":"Seydikemer","population":61653,"area":2208},{"name":"Ula","population":25402,"area":479},{"name":"Yatağan","population":44879,"area":851}]},
{"name":"Muş","districts":[{"name":"Bulanık","population":80643,"area":56},{"name":"Hasköy","population":26190,"area":17},{"name":"Korkut","population":24830,"area":30},{"name":"Malazgirt","population":50926,"area":74},{"name":"Merkez","population":195323,"area":94},{"name":"Varto","population":30897,"area":93}]},
{"name":"Nevşehir","districts":[{"name":"Acıgöl","population":19362,"area":10},{"name":"Avanos","population":32742,"area":16},{"name":"Derinkuyu","population":20776,"area":7},{"name":"Gülşehir","population":21468,"area":31},{"name":"Hacıbektaş","population":11302,"area":30},{"name":"Kozaklı","population":13379,"area":27},{"name":"Merkez","population":148160,"area":9},{"name":"Ürgüp","population":35821,"area":23}]},
{"name":"Niğde","districts":[{"name":"Altunhisar","population":12961,"area":6},{"name":"Bor","population":60462,"area":23},{"name":"Çamardı","population":12715,"area":21},{"name":"Çiftlik","population":27374,"area":9},{"name":"Merkez","population":229121,"area":33},{"name":"Ulukışla","population":20228,"area":38}]},
{"name":"Ordu","districts":[{"name":"Akkuş","population":22192,"area":697},{"name":"Altınordu","population":217640,"area":410},{"name":"Aybastı","population":22027,"area":250},{"name":"Çamaş","population":9058,"area":81},{"name":"Çatalpınar","population":13809,"area":101},{"name":"Çaybaşı","population":12687,"area":102},{"name":"Fatsa","population":119094,"area":363},{"name":"Gölköy","population":28332,"area":421},{"name":"Gülyalı","population":8269,"area":62},{"name":"Gürgentepe","population":14100,"area":185},{"name":"İkizce","population":14570,"area":148},{"name":"Kabadüz","population":7347,"area":290},{"name":"Kabataş","population":10617,"area":74},{"name":"Korgan","population":28609,"area":254},{"name":"Kumru","population":29945,"area":296},{"name":"Mesudiye","population":16809,"area":1046},{"name":"Perşembe","population":31542,"area":217},{"name":"Ulubey","population":19450,"area":295},{"name":"Ünye","population":128101,"area":569}]},
{"name":"Osmaniye","districts":[{"name":"Bahçe","population":22155,"area":15},{"name":"Düziçi","population":84133,"area":25},{"name":"Hasanbeyli","population":4782,"area":6},{"name":"Kadirli","population":125083,"area":60},{"name":"Merkez","population":268647,"area":37},{"name":"Sumbas","population":13840,"area":13},{"name":"Toprakkale","population":20119,"area":3}]},
{"name":"Rize","districts":[{"name":"Ardeşen","population":41106,"area":40},{"name":"Çamlıhemşin","population":7147,"area":24},{"name":"Çayeli","population":44351,"area":54},{"name":"Derepazarı","population":7653,"area":11},{"name":"Fındıklı","population":16678,"area":23},{"name":"Güneysu","population":15596,"area":21},{"name":"Hemşin","population":2478,"area":8},{"name":"İkizdere","population":7135,"area":29},{"name":"İyidere","population":8554,"area":7},{"name":"Kalkandere","population":13708,"area":22},{"name":"Merkez","population":147411,"area":60},{"name":"Pazar","population":31395,"area":48}]},
{"name":"Sakarya","districts":[{"name":"Adapazarı","population":276385,"area":324},{"name":"Akyazı","population":90362,"area":628},{"name":"Arifiye","population":45375,"area":75},{"name":"Erenler","population":89128,"area":136},{"name":"Ferizli","population":27347,"area":173},{"name":"Geyve","population":49958,"area":662},{"name":"Hendek","population":85570,"area":646},{"name":"Karapürçek","population":12982,"area":142},{"name":"Karasu","population":64790,"area":411},{"name":"Kaynarca","population":24138,"area":343},{"name":"Kocaali","population":22938,"area":254},{"name":"Pamukova","population":29740,"area":289},{"name":"Sapanca","population":42416,"area":173},{"name":"Serdivan","population":147500,"area":130},{"name":"Söğütlü","population":14088,"area":145},{"name":"Taraklı","population":6933,"area":292}]},
{"name":"Samsun","districts":[{"name":"Alaçam","population":25430,"area":598},{"name":"Asarcık","population":16778,"area":253},{"name":"Atakum","population":215633,"area":351},{"name":"Ayvacık","population":20443,"area":382},{"name":"Bafra","population":142761,"area":1503},{"name":"Canik","population":99149,"area":264},{"name":"Çarşamba","population":138544,"area":774},{"name":"Havza","population":39656,"area":865},{"name":"İlkadım","population":338614,"area":155},{"name":"Kavak","population":21074,"area":697},{"name":"Ladik","population":16368,"area":541},{"name":"Ondokuzmayıs","population":25893,"area":234},{"name":"Salıpazarı","population":19990,"area":356},{"name":"Tekkeköy","population":52935,"area":326},{"name":"Terme","population":71492,"area":548},{"name":"Vezirköprü","population":95097,"area":1674},{"name":"Yakakent","population":8685,"area":204}]},
{"name":"Siirt","districts":[{"name":"Baykan","population":25275,"area":30},{"name":"Eruh","population":18931,"area":54},{"name":"Kurtalan","population":60180,"area":55},{"name":"Merkez","population":168659,"area":35},{"name":"Pervari","population":30858,"area":38},{"name":"Şirvan","population":22117,"area":57},{"name":"Tillo","population":4260,"area":6}]},{"name":"Sinop","districts":[{"name":"Ayancık","population":23686,"area":71},{"name":"Boyabat","population":44435,"area":107},{"name":"Dikmen","population":5016,"area":28},{"name":"Durağan","population":19815,"area":70},{"name":"Erfelek","population":11926,"area":46},{"name":"Gerze","population":25327,"area":42},{"name":"Merkez","population":65845,"area":38},{"name":"Saraydüzü","population":6334,"area":30},{"name":"Türkeli","population":15859,"area":33}]},
{"name":"Sivas","districts":[{"name":"Akıncılar","population":5326,"area":29},{"name":"Altınyayla","population":9004,"area":10},{"name":"Divriği","population":16245,"area":105},{"name":"Doğanşar","population":2842,"area":26},{"name":"Gemerek","population":22845,"area":34},{"name":"Gölova","population":3664,"area":29},{"name":"Gürün","population":18771,"area":60},{"name":"Hafik","population":9819,"area":74},{"name":"İmranlı","population":7668,"area":100},{"name":"Kangal","population":21272,"area":112},{"name":"Koyulhisar","population":12936,"area":44},{"name":"Merkez","population":381325,"area":153},{"name":"Suşehri","population":25159,"area":71},{"name":"Şarkışla","population":38408,"area":95},{"name":"Ulaş","population":8870,"area":38},{"name":"Yıldızeli","population":32797,"area":118},{"name":"Zara","population":22005,"area":135}]},
{"name":"Şanlıurfa","districts":[{"name":"Akçakale","population":115615,"area":1038},{"name":"Birecik","population":95128,"area":912},{"name":"Bozova","population":55423,"area":1329},{"name":"Ceylanpınar","population":89020,"area":1589},{"name":"Eyyübiye","population":379852,"area":1626},{"name":"Halfeti","population":40879,"area":609},{"name":"Haliliye","population":381877,"area":1924},{"name":"Harran","population":89798,"area":904},{"name":"Hilvan","population":42724,"area":1111},{"name":"Karaköprü","population":219796,"area":1222},{"name":"Siverek","population":260970,"area":3936},{"name":"Suruç","population":102265,"area":744},{"name":"Viranşehir","population":200267,"area":2297}]},
{"name":"Şırnak","districts":[{"name":"Beytüşşebap","population":16330,"area":26},{"name":"Cizre","population":148697,"area":31},{"name":"Güçlükonak","population":12295,"area":18},{"name":"İdil","population":76895,"area":63},{"name":"Merkez","population":93989,"area":19},{"name":"Silopi","population":136749,"area":26},{"name":"Uludere","population":44660,"area":13}]},
{"name":"Tekirdağ","districts":[{"name":"Çerkezköy","population":174529,"area":86},{"name":"Çorlu","population":270944,"area":531},{"name":"Ergene","population":63821,"area":418},{"name":"Hayrabolu","population":32268,"area":1009},{"name":"Kapaklı","population":120489,"area":182},{"name":"Malkara","population":52453,"area":1243},{"name":"Marmaraereğlisi","population":26007,"area":175},{"name":"Muratlı","population":29028,"area":388},{"name":"Saray","population":49605,"area":620},{"name":"Süleymanpaşa","population":204001,"area":1053},{"name":"Şarköy","population":32267,"area":487}]},
{"name":"Tokat","districts":[{"name":"Almus","population":27658,"area":32},{"name":"Artova","population":8374,"area":26},{"name":"Başçiftlik","population":8323,"area":6},{"name":"Erbaa","population":95611,"area":74},{"name":"Merkez","population":199805,"area":107},{"name":"Niksar","population":65308,"area":83},{"name":"Pazar","population":13330,"area":16},{"name":"Reşadiye","population":43870,"area":73},{"name":"Sulusaray","population":7598,"area":14},{"name":"Turhal","population":79604,"area":52},{"name":"Yeşilyurt","population":8969,"area":16},{"name":"Zile","population":54297,"area":114}]},
{"name":"Trabzon","districts":[{"name":"Akçaabat","population":125848,"area":375},{"name":"Araklı","population":48660,"area":464},{"name":"Arsin","population":32063,"area":157},{"name":"Beşikdüzü","population":23328,"area":84},{"name":"Çarşıbaşı","population":15562,"area":66},{"name":"Çaykara","population":14379,"area":574},{"name":"Dernekpazarı","population":3986,"area":89},{"name":"Düzköy","population":13909,"area":125},{"name":"Hayrat","population":8490,"area":244},{"name":"Köprübaşı","population":4851,"area":189},{"name":"Maçka","population":25363,"area":925},{"name":"Of","population":43082,"area":258},{"name":"Ortahisar","population":328457,"area":235},{"name":"Sürmene","population":26824,"area":166},{"name":"Şalpazarı","population":11015,"area":161},{"name":"Tonya","population":14116,"area":176},{"name":"Vakfıkebir","population":27525,"area":141},{"name":"Yomra","population":41516,"area":200}]},
{"name":"Tunceli","districts":[{"name":"Çemişgezek","population":7877,"area":34},{"name":"Hozat","population":6255,"area":28},{"name":"Mazgirt","population":7778,"area":68},{"name":"Merkez","population":38427,"area":53},{"name":"Nazımiye","population":3189,"area":25},{"name":"Ovacık","population":6696,"area":62},{"name":"Pertek","population":11063,"area":45},{"name":"Pülümür","population":3375,"area":49}]},
{"name":"Uşak","districts":[{"name":"Banaz","population":35778,"area":46},{"name":"Eşme","population":34888,"area":59},{"name":"Karahallı","population":10139,"area":13},{"name":"Merkez","population":256669,"area":83},{"name":"Sivaslı","population":20387,"area":18},{"name":"Ulubey","population":12648,"area":26}]},
{"name":"Van","districts":[{"name":"Bahçesaray","population":14701,"area":426},{"name":"Başkale","population":48838,"area":2727},{"name":"Çaldıran","population":62530,"area":1478},{"name":"Çatak","population":20592,"area":1952},{"name":"Edremit","population":127505,"area":515},{"name":"Erciş","population":175108,"area":2133},{"name":"Gevaş","population":28235,"area":1544},{"name":"Gürpınar","population":34393,"area":4028},{"name":"İpekyolu","population":326007,"area":956},{"name":"Muradiye","population":50206,"area":912},{"name":"Özalp","population":65296,"area":1430},{"name":"Saray","population":20498,"area":872},{"name":"Tuşba","population":162848,"area":1948}]},
{"name":"Yalova","districts":[{"name":"Altınova","population":29237,"area":12},{"name":"Armutlu","population":9543,"area":5},{"name":"Çınarcık","population":34343,"area":4},{"name":"Çiftlikköy","population":41882,"area":9},{"name":"Merkez","population":149068,"area":11},{"name":"Termal","population":6903,"area":2}]},
{"name":"Yozgat","districts":[{"name":"Akdağmadeni","population":42621,"area":78},{"name":"Aydıncık","population":10079,"area":22},{"name":"Boğazlıyan","population":34269,"area":22},{"name":"Çandır","population":4450,"area":4},{"name":"Çayıralan","population":12563,"area":23},{"name":"Çekerek","population":19467,"area":41},{"name":"Kadışehri","population":11277,"area":20},{"name":"Merkez","population":106280,"area":96},{"name":"Saraykent","population":12486,"area":14},{"name":"Sarıkaya","population":32489,"area":56},{"name":"Sorgun","population":79533,"area":74},{"name":"Şefaatli","population":14824,"area":41},{"name":"Yenifakılı","population":5386,"area":7},{"name":"Yerköy","population":35476,"area":60}]},
{"name":"Zonguldak","districts":[{"name":"Alaplı","population":43851,"area":52},{"name":"Çaycuma","population":90556,"area":83},{"name":"Devrek","population":57583,"area":83},{"name":"Ereğli","population":175622,"area":93},{"name":"Gökçebey","population":21108,"area":19},{"name":"Kilimli","population":34829,"area":4},{"name":"Kozlu","population":48507,"area":23},{"name":"Merkez","population":123997,"area":23}]}]